espa_api_client/Clients.py
espa_api_client/Downloaders.py
espa_api_client/Exceptions.py
espa_api_client/Order.py
espa_api_client/OrderTemplate.py
espa_api_client/__init__.py
espa_api_client/conf.py
espa_api_client/parse.py
espa_api_client/search.py
espa_api_client-1.0.0.dev27.dist-info/DESCRIPTION.rst
espa_api_client-1.0.0.dev27.dist-info/METADATA
espa_api_client-1.0.0.dev27.dist-info/RECORD
espa_api_client-1.0.0.dev27.dist-info/WHEEL
espa_api_client-1.0.0.dev27.dist-info/metadata.json
espa_api_client-1.0.0.dev27.dist-info/top_level.txt
test/__init__.py
test/parse_test.py
