Metadata-Version: 2.0
Name: espa-api-client
Version: 1.0.0.dev27
Summary: Python interface to the espa-api
Home-page: https://github.com/Jwely/espa-api-client
Author: Jwely
Author-email: jeff.ely.08@gmail.com
License: MIT
Keywords: landsat,modis,espa,ordering
Platform: UNKNOWN
Classifier: Development Status :: 3 - Alpha
Classifier: Intended Audience :: Developers
Classifier: Topic :: Software Development
Classifier: License :: OSI Approved :: MIT License
Classifier: Programming Language :: Python :: 2.7
Classifier: Programming Language :: Python :: 3
Classifier: Programming Language :: Python :: 3.3
Classifier: Programming Language :: Python :: 3.4
Classifier: Programming Language :: Python :: 3.5
Classifier: Programming Language :: Python :: 3.6
Requires-Dist: pandas
Requires-Dist: requests
Requires-Dist: wget
Provides-Extra: dev
Provides-Extra: test
